LICENSE
MANIFEST.in
README.rst
setup.py
client/thunderpush.js
examples/angularjs.html
examples/apiconsole.html
examples/basic.html
thunderpush/__init__.py
thunderpush/api.py
thunderpush/handler.py
thunderpush/messenger.py
thunderpush/runner.py
thunderpush/settings.py
thunderpush/sortingstation.py
thunderpush.egg-info/PKG-INFO
thunderpush.egg-info/SOURCES.txt
thunderpush.egg-info/dependency_links.txt
thunderpush.egg-info/entry_points.txt
thunderpush.egg-info/not-zip-safe
thunderpush.egg-info/requires.txt
thunderpush.egg-info/top_level.txt
thunderpush/tests/__init__.py
thunderpush/tests/mocks.py
thunderpush/tests/test_api.py
thunderpush/tests/test_cli.py
thunderpush/tests/test_messenger.py