Metadata-Version: 1.1
Name: thunderpush
Version: 1.0.1
Summary: Tornado and SockJS based, complete Web push solution.
Home-page: https://github.com/thunderpush/thunderpush
Author: Krzysztof Jagiello
Author-email: me@kjagiello.com
License: BSD
Platform: UNKNOWN
Classifier: Programming Language :: Python
Classifier: Programming Language :: Python :: 3
Classifier: Intended Audience :: Developers
Classifier: License :: OSI Approved :: BSD License
Classifier: Operating System :: OS Independent
Classifier: Topic :: Internet
